AUTHORS
LICENCE
MANIFEST.in
setup.py
cmskit/.DS_Store
cmskit/articles/__init__.py
cmskit/articles/__init__.pyc
cmskit/articles/admin.py
cmskit/articles/admin.pyc
cmskit/articles/cms_app.py
cmskit/articles/cms_app.pyc
cmskit/articles/cms_plugins.py
cmskit/articles/cms_plugins.pyc
cmskit/articles/forms.py
cmskit/articles/forms.pyc
cmskit/articles/managers.py
cmskit/articles/managers.pyc
cmskit/articles/menu.py
cmskit/articles/menu.pyc
cmskit/articles/models.py
cmskit/articles/models.pyc
cmskit/articles/search_indexes.py
cmskit/articles/search_indexes.pyc
cmskit/articles/sitemaps.py
cmskit/articles/sitemaps.pyc
cmskit/articles/urls.py
cmskit/articles/urls.pyc
cmskit/articles/views.py
cmskit/articles/views.pyc
cmskit/articles/migrations/0001_initial.py
cmskit/articles/migrations/0001_initial.pyc
cmskit/articles/migrations/__init__.py
cmskit/articles/migrations/__init__.pyc
cmskit/articles/templates/.DS_Store
cmskit/articles/templates/articles/_breadcrumb.html
cmskit/articles/templates/articles/_index.html
cmskit/articles/templates/articles/_latest.html
cmskit/articles/templates/articles/_teaser.html
cmskit/articles/templates/articles/article.html
cmskit/articles/templates/articles/breadcrumb.html
cmskit/articles/templates/articles/index.html
cmskit/articles/templates/search/articles/article_index.txt
cmskit/contact/.DS_Store
cmskit/contact/__init__.py
cmskit/contact/__init__.pyc
cmskit/contact/admin.py
cmskit/contact/admin.pyc
cmskit/contact/cms_plugins.py
cmskit/contact/cms_plugins.pyc
cmskit/contact/forms.py
cmskit/contact/forms.pyc
cmskit/contact/models.py
cmskit/contact/models.pyc
cmskit/contact/migrations/0001_initial.py
cmskit/contact/migrations/0001_initial.pyc
cmskit/contact/migrations/__init__.py
cmskit/contact/migrations/__init__.pyc
cmskit/contact/nospam/__init__.py
cmskit/contact/nospam/__init__.pyc
cmskit/contact/nospam/fields.py
cmskit/contact/nospam/fields.pyc
cmskit/contact/nospam/forms.py
cmskit/contact/nospam/forms.pyc
cmskit/contact/nospam/utils.py
django_cmskit.egg-info/PKG-INFO
django_cmskit.egg-info/SOURCES.txt
django_cmskit.egg-info/dependency_links.txt
django_cmskit.egg-info/not-zip-safe
django_cmskit.egg-info/requires.txt
django_cmskit.egg-info/top_level.txt