Metadata-Version: 1.0
Name: django-cmskit
Version: 0.1b0
Summary: A collection of useful Django CMS extensions.
Home-page: http://github.com/ozgurgunes/django-cmskit/
Author: Ozgur Gunes
Author-email: o.gunes@gmail.com
License: UNKNOWN
Platform: UNKNOWN
Classifier: Development Status :: 1 - Planning
Classifier: Environment :: Web Environment
Classifier: Intended Audience :: Developers
Classifier: License :: OSI Approved :: MIT License
Classifier: Operating System :: OS Independent
Classifier: Programming Language :: Python
Classifier: Framework :: Django
